rarity_tools_scraper/__init__.py
rarity_tools_scraper/collections.py
rarity_tools_scraper/data.py
rarity_tools_scraper/projects.py
rarity_tools_scraper-0.0.11.dist-info/LICENSE
rarity_tools_scraper-0.0.11.dist-info/METADATA
rarity_tools_scraper-0.0.11.dist-info/WHEEL
rarity_tools_scraper-0.0.11.dist-info/top_level.txt
rarity_tools_scraper-0.0.11.dist-info/RECORD
